<?xml version="1.0" encoding="UTF-8"?>
<objects serializationModel="Studio.02.02.00">
	<object class="Workspace" id="{ce80f1be-c774-4218-88b4-755747cb63e2}">
		<relationship name="projectSettings">
			<destination>{e35c705e-0cc2-45f1-bde2-f4aec3a2ff79}</destination>
		</relationship>
	</object>
	<object class="ProjectSettings" id="{e35c705e-0cc2-45f1-bde2-f4aec3a2ff79}">
		<relationship name="activePlatform">
			<destination>{52b0e7b0-e906-4ffe-bcbe-0198d28ea1a2}</destination>
		</relationship>
	</object>
</objects>
